hloenv/__init__.py
hloenv-0.0.0.dist-info/METADATA
hloenv-0.0.0.dist-info/WHEEL
hloenv-0.0.0.dist-info/top_level.txt
hloenv-0.0.0.dist-info/RECORD
