Metadata-Version: 2.1
Name: hloenv
Version: 0.0.0
Summary: "hloenv"
Home-page: https://github.com/sail-sg/hloenv.git
Author: "sail developers"
Author-email: "sail@sea.com"
Project-URL: Bug Tracker, https://github.com/sail-sg/hloenv/issues
Classifier: Programming Language :: Python :: 3
Classifier: License :: OSI Approved :: MIT License
Classifier: Operating System :: OS Independent
Requires-Python: >=3.6
